{
  "generator-jhipster": {
    "promptValues": {
      "packageName": "com.tothapplication",
      "nativeLanguage": "fr"
    },
    "jhipsterVersion": "6.1.2",
    "applicationType": "monolith",
    "baseName": "TothApplication",
    "packageName": "com.tothapplication",
    "packageFolder": "com/tothapplication",
    "serverPort": "8080",
    "authenticationType": "jwt",
    "cacheProvider": "ehcache",
    "enableHibernateCache": true,
    "websocket": false,
    "databaseType": "sql",
    "devDatabaseType": "postgresql",
    "prodDatabaseType": "postgresql",
    "searchEngine": false,
    "messageBroker": false,
    "serviceDiscoveryType": false,
    "buildTool": "maven",
    "enableSwaggerCodegen": false,
    "jwtSecretKey": "NmFjMjhiYjdhZTNiNDg3ZDE1OGQ4NDJlMTQzZjQ2ZDMwODdlNmIyNmNlOWRmYjg4Yzc0Njc1MmIxYmY5NDdjNjQzNGRjZTU5YzBhODViMTExMDU5MzMyN2I0ZTg5MGEzZmM2NWFkOTBhZDQyZWY1NjlkNzJiMjdhYzg1OThlODQ=",
    "useSass": true,
    "clientPackageManager": "npm",
    "clientFramework": "angularX",
    "clientTheme": "united",
    "clientThemeVariant": "primary",
    "testFrameworks": ["protractor"],
    "jhiPrefix": "jhi",
    "entitySuffix": "",
    "dtoSuffix": "DTO",
    "otherModules": [
      {
        "name": "generator-jhipster-primeng-charts",
        "version": "1.2.0"
      },
      {
        "name": "generator-jhipster-angular-material-integration",
        "version": "1.0.17"
      }
    ],
    "enableTranslation": true,
    "nativeLanguage": "fr",
    "languages": ["fr", "en"]
  }
}
